tekton_pipeline/__init__.py
tekton_pipeline/api_client.py
tekton_pipeline/configuration.py
tekton_pipeline/exceptions.py
tekton_pipeline/rest.py
tekton_pipeline/api/__init__.py
tekton_pipeline/api/tekton_client.py
tekton_pipeline/constants/__init__.py
tekton_pipeline/constants/constants.py
tekton_pipeline/models/__init__.py
tekton_pipeline/models/pod_template.py
tekton_pipeline/models/v1alpha1_pipeline_resource.py
tekton_pipeline/models/v1alpha1_pipeline_resource_list.py
tekton_pipeline/models/v1alpha1_pipeline_resource_spec.py
tekton_pipeline/models/v1alpha1_resource_declaration.py
tekton_pipeline/models/v1alpha1_resource_param.py
tekton_pipeline/models/v1alpha1_secret_param.py
tekton_pipeline/models/v1beta1_array_or_string.py
tekton_pipeline/models/v1beta1_cannot_convert_error.py
tekton_pipeline/models/v1beta1_cloud_event_delivery.py
tekton_pipeline/models/v1beta1_cloud_event_delivery_state.py
tekton_pipeline/models/v1beta1_cluster_task.py
tekton_pipeline/models/v1beta1_cluster_task_list.py
tekton_pipeline/models/v1beta1_condition_check.py
tekton_pipeline/models/v1beta1_condition_check_status.py
tekton_pipeline/models/v1beta1_condition_check_status_fields.py
tekton_pipeline/models/v1beta1_embedded_task.py
tekton_pipeline/models/v1beta1_internal_task_modifier.py
tekton_pipeline/models/v1beta1_param.py
tekton_pipeline/models/v1beta1_param_spec.py
tekton_pipeline/models/v1beta1_pipeline.py
tekton_pipeline/models/v1beta1_pipeline_declared_resource.py
tekton_pipeline/models/v1beta1_pipeline_list.py
tekton_pipeline/models/v1beta1_pipeline_ref.py
tekton_pipeline/models/v1beta1_pipeline_resource_binding.py
tekton_pipeline/models/v1beta1_pipeline_resource_ref.py
tekton_pipeline/models/v1beta1_pipeline_resource_result.py
tekton_pipeline/models/v1beta1_pipeline_result.py
tekton_pipeline/models/v1beta1_pipeline_run.py
tekton_pipeline/models/v1beta1_pipeline_run_condition_check_status.py
tekton_pipeline/models/v1beta1_pipeline_run_list.py
tekton_pipeline-0.2.0.dist-info/METADATA
tekton_pipeline-0.2.0.dist-info/WHEEL
tekton_pipeline-0.2.0.dist-info/top_level.txt
tekton_pipeline-0.2.0.dist-info/RECORD
